{
  "bake": {
    "push": false,
    "platforms": [],
    "tags": [],
    "args": {},
    "cache": {
      "from": [
        "type=registry,ref=registry.depot.dev/f5k5087x1b:monorepo-bake-cache-v1-plugins_libstoml-ops"
      ],
      "to": [
        "type=registry,ref=registry.depot.dev/f5k5087x1b:monorepo-bake-cache-v1-plugins_libstoml-ops,mode=min,image-manifest=true,oci-mediatypes=true"
      ]
    }
  },
  "dockerfile": {
    "preamble": [],
    "from": null,
    "mounts": [],
    "secrets": {},
    "extra_hosts": [],
    "epilogue": [],
    "copy": [],
    "healthcheck": null,
    "expose": [],
    "entrypoint": null,
    "incremental": false,
    "cmd": null
  },
  "name": "ops",
  "project": "plugins_libstoml",
  "dir": "plugins/libstoml",
  "activate": "mise x --",
  "srcs": {
    "globs": [
      "compose.yaml",
      ".bayt/**"
    ],
    "exclude": []
  },
  "outs": {
    "globs": [
      "compose.yaml",
      ".bayt/**"
    ],
    "exclude": []
  },
  "env": {},
  "visibility": "public",
  "deps": [
    "ops"
  ],
  "transitiveDeps": [],
  "transitiveCrossDeps": [
    {
      "name": "ops",
      "project": "workspaceroot",
      "dir": "",
      "outs": {
        "globs": [
          ".bayt/**",
          "Taskfile.yml",
          "compose.yaml",
          "plugins/devserver/dind.sh"
        ],
        "exclude": []
      }
    }
  ],
  "chainedDeps": [
    {
      "name": "ops",
      "project": "workspaceroot",
      "dir": "",
      "outs": {
        "globs": [
          ".bayt/**",
          "Taskfile.yml",
          "compose.yaml",
          "plugins/devserver/dind.sh"
        ],
        "exclude": []
      }
    }
  ],
  "cmds": [],
  "cache": {
    "full": false,
    "similar": false
  }
}